{
  "id": "1816403",
  "name": "职工健康管理",
  "font_family": "iconfont",
  "css_prefix_text": "icon-",
  "description": "",
  "glyphs": [
    {
      "icon_id": "17071519",
      "name": "logo文字",
      "font_class": "logowenzi",
      "unicode": "e605",
      "unicode_decimal": 58885
    },
    {
      "icon_id": "16969716",
      "name": "全人logo",
      "font_class": "quanrenlogo1",
      "unicode": "e604",
      "unicode_decimal": 58884
    },
    {
      "icon_id": "15901458",
      "name": "填写信息",
      "font_class": "tianxiexinxi",
      "unicode": "e603",
      "unicode_decimal": 58883
    },
    {
      "icon_id": "15901456",
      "name": "新增员工",
      "font_class": "xinzengyuangong1",
      "unicode": "e602",
      "unicode_decimal": 58882
    },
    {
      "icon_id": "15900456",
      "name": "添加标准",
      "font_class": "tianjiabiaozhun1",
      "unicode": "e601",
      "unicode_decimal": 58881
    },
    {
      "icon_id": "3892530",
      "name": "体检受理",
      "font_class": "taocan",
      "unicode": "e65c",
      "unicode_decimal": 58972
    },
    {
      "icon_id": "1315601",
      "name": "医院",
      "font_class": "tijianzhongxin",
      "unicode": "e607",
      "unicode_decimal": 58887
    },
    {
      "icon_id": "4237398",
      "name": "体检信息",
      "font_class": "tijianjihua",
      "unicode": "e638",
      "unicode_decimal": 58936
    },
    {
      "icon_id": "12842809",
      "name": "w_职员",
      "font_class": "w_zhiyuan",
      "unicode": "e67e",
      "unicode_decimal": 59006
    },
    {
      "icon_id": "13332705",
      "name": "系统-1",
      "font_class": "xitong",
      "unicode": "e60f",
      "unicode_decimal": 58895
    },
    {
      "icon_id": "15711337",
      "name": "全人logo",
      "font_class": "quanrenlogo",
      "unicode": "e600",
      "unicode_decimal": 58880
    },
    {
      "icon_id": "14929831",
      "name": "上下左右Triangle1 (1)",
      "font_class": "shangxiazuoyouTriangle11",
      "unicode": "e690",
      "unicode_decimal": 59024
    },
    {
      "icon_id": "14929834",
      "name": "上下左右Triangle1 (2)",
      "font_class": "shangxiazuoyouTriangle12",
      "unicode": "e691",
      "unicode_decimal": 59025
    },
    {
      "icon_id": "5269224",
      "name": "会员",
      "font_class": "huiyuan",
      "unicode": "e625",
      "unicode_decimal": 58917
    },
    {
      "icon_id": "7140560",
      "name": "基础设置",
      "font_class": "jichushezhi",
      "unicode": "e63f",
      "unicode_decimal": 58943
    }
  ]
}
